pyxfoil/__init__.py
pyxfoil/xfoil.py
pyxfoil/xfoilpolar.py
pyxfoil/xfoilresult.py
pyxfoil-0.0.2.dist-info/LICENSE
pyxfoil-0.0.2.dist-info/METADATA
pyxfoil-0.0.2.dist-info/WHEEL
pyxfoil-0.0.2.dist-info/top_level.txt
pyxfoil-0.0.2.dist-info/RECORD
