Metadata-Version: 2.1
Name: pyxfoil
Version: 0.0.2
Summary: Run XFoil from within Python and work with output results.
Home-page: https://github.com/Xero64/pyxfoil
Author: Xero64
Author-email: xero64@gmail.com
Classifier: Programming Language :: Python :: 3
Classifier: License :: OSI Approved :: MIT License
Classifier: Operating System :: OS Independent
Requires-Python: >=3.7
License-File: LICENSE
